danak/__init__.py
danak/base.py
danak/fields.py
danak/migrations.py
danak/query.py
danak/validators.py
danak-0.0.1.dist-info/METADATA
danak-0.0.1.dist-info/WHEEL
danak-0.0.1.dist-info/top_level.txt
danak-0.0.1.dist-info/RECORD
