Metadata-Version: 2.1
Name: danak
Version: 0.0.1
Summary: danak - Lightweight Python ORM
Home-page: https://github.com/mehmonov/danak
Author: Mehmonov Husniddin
Author-email: mehmonov.husniddin1@gmail.com
License: MIT
Classifier: License :: OSI Approved :: MIT License
Classifier: Programming Language :: Python
Classifier: Programming Language :: Python :: 3
Classifier: Programming Language :: Python :: 3.6
Classifier: Programming Language :: Python :: Implementation :: CPython
Classifier: Programming Language :: Python :: Implementation :: PyPy
Requires-Python: >=3.11.0
